cgmix2
gmix2
