Metadata-Version: 2.1
Name: gmix2
Version: 0.0.1
Summary: An implementation of Gaussian mixture distribution methods
Home-page: https://bitbucket.org/reidswanson/gmix2
Author: Reid Swanson
Author-email: reid@reidswanson.com
Maintainer: Reid Swanson
Maintainer-email: reid@reidswanson.com
License: Apache-2.0
Platform: UNKNOWN
Classifier: Development Status :: 4 - Beta
Classifier: Intended Audience :: Science/Research
Classifier: License :: OSI Approved :: Apache Software License
Classifier: Natural Language :: English
Classifier: Operating System :: MacOS
Classifier: Operating System :: Microsoft :: Windows
Classifier: Operating System :: POSIX
Classifier: Operating System :: Unix
Classifier: Programming Language :: Python :: 3.7
Classifier: Topic :: Scientific/Engineering :: Mathematics
Provides-Extra: plotting
